{
  "status": "ok",
  "totalResults": 1,
  "articles": [
    {
      "source": {
        "id": "business-insider",
        "name": "Business Insider"
      },
      "author": "Daniel Geiger",
      "title": "For crypto miners turned AI stars, the real test is about to come",
      "description": "Meet the quiet winners of the AI boom, the crypto mining players pivoting to big opportunities in the AI boom.",
      "url": "https://www.businessinsider.com/crypto-miners-ai-data-centers-big-tech-infrastructure-apld-iren-2026-4",
      "urlToImage": "https://i.insider.com/69d03c956a864f6fcd7bd5b5?width=1200&format=jpeg",
      "publishedAt": "2026-04-05T10:43:01Z",
      "content": "A Bitdeer Technologies cryptocurrency mining data center under construction in Massillon, Ohio.Bloomberg/Getty Images; Tyler Le/BI\r\n<ul><li>Former crypto miners are pivoting to AI, leveraging legacy \u2026 [+7794 chars]"
    }
  ]
}